TICC-0.1.6.dist-info/LICENSE.txt
TICC-0.1.6.dist-info/METADATA
TICC-0.1.6.dist-info/RECORD
TICC-0.1.6.dist-info/WHEEL
TICC-0.1.6.dist-info/top_level.txt
ticc/RunProblem.py
ticc/__init__.py
