Metadata-Version: 2.1
Name: TICC
Version: 0.1.6
Summary: Solver for Toeplitz Inverse Covariance-based Clustering (TICC)
Home-page: https://github.com/davidhallac/ticc
Author: UNKNOWN
Author-email: UNKNOWN
License: UNKNOWN
Download-URL: https://github.com/davidhallac/TICC/blob/blackbox/tarFile/TICC-0.1.6.tar.gz
Platform: UNKNOWN
Requires-Dist: numpy
Requires-Dist: scipy
Requires-Dist: matplotlib
Requires-Dist: pandas
Requires-Dist: scikit-learn
